{
  "schemaVersion": 1,
  "id": "cobblemonextras",
  "version": "${version}",
  "name": "CobblemonExtras",
  "description": "Your one stop shop for all your extra Cobblemon needs.\n\n",
  "authors": [
    "The Cobblemon Extas Team"
  ],
  "contact": {
    "homepage": "https://cobblemon.com/",
    "sources": "https://github.com/Xwaffle1/CobblemonExtras",
    "issues": "https://github.com/Xwaffle1/CobblemonExtras-/issues"
  },
  "environment": "server",
  "entrypoints": {
    "main": [
      "dev.chasem.cobblemonextras.fabric.CobblemonFabric"
    ],
    "client": []
  },
  "mixins": [
    "mixins.cobblemonextras-common.json"
  ],
  "depends": {
    "fabricloader": ">=0.14.21",
    "fabric": ">=0.89.0",
    "fabric-api": "*",
    "minecraft": ">=1.21.0",
    "java": ">=21",
    "cobblemon": ">=1.6.0"
  },
  "custom": {
    "modmenu": {
      "links": {
        "modmenu.modrinth": "https://modrinth.com/mod/cobblemonextras"
      }
    }
  }
}